adaptive_dynamics/__init__.py
adaptive_dynamics/arp/__init__.py
adaptive_dynamics/arp/arp_ode.py
adaptive_dynamics/arp/optimizers.py
adaptive_dynamics/core/__init__.py
adaptive_dynamics/core/config.py
adaptive_dynamics/core/numerics.py
adaptive_dynamics/core/registry.py
adaptive_dynamics/pi/__init__.py
adaptive_dynamics/pi/gauss_bonnet.py
adaptive_dynamics/pi/geometry.py
adaptive_dynamics/tsp/__init__.py
adaptive_dynamics/tsp/slicer.py
adaptive_dynamics-0.1.0.dist-info/METADATA
adaptive_dynamics-0.1.0.dist-info/WHEEL
adaptive_dynamics-0.1.0.dist-info/licenses/LICENSE
adaptive_dynamics-0.1.0.dist-info/RECORD
