Metadata-Version: 2.4
Name: adaptive-dynamics
Version: 0.1.0
Summary: Adaptive Dynamics Toolkit: Adaptive π geometry, ARP optimizers, simulations, and compression.
Project-URL: Homepage, https://github.com/rdm3dc/adaptive-dynamics-toolkit
Project-URL: Documentation, https://rdm3dc.github.io/adaptive-dynamics-toolkit/
Project-URL: Source, https://github.com/rdm3dc/adaptive-dynamics-toolkit
Project-URL: Issues, https://github.com/rdm3dc/adaptive-dynamics-toolkit/issues
Author-email: Ryan McKenna <contact@rdm3dc.dev>
License: MIT License
License-File: LICENSE
Keywords: compression,geometry,optimization,physics,torch
Classifier: Intended Audience :: Science/Research
Classifier: License :: OSI Approved :: MIT License
Classifier: Operating System :: OS Independent
Classifier: Programming Language :: Python :: 3
Classifier: Topic :: Scientific/Engineering
Requires-Python: >=3.10
Requires-Dist: matplotlib>=3.7
Requires-Dist: numpy>=1.24
Requires-Dist: scipy>=1.11
Provides-Extra: cuda
Requires-Dist: cupy-cuda12x>=12.0; extra == 'cuda'
Provides-Extra: dev
Requires-Dist: mypy>=1.10; extra == 'dev'
Requires-Dist: pytest-cov>=4.1; extra == 'dev'
Requires-Dist: pytest>=8.0; extra == 'dev'
Requires-Dist: ruff>=0.5; extra == 'dev'
Provides-Extra: docs
Requires-Dist: mkdocs-material>=9.5; extra == 'docs'
Requires-Dist: mkdocstrings[python]>=0.24; extra == 'docs'
Provides-Extra: sympy
Requires-Dist: sympy>=1.12; extra == 'sympy'
Provides-Extra: torch
Requires-Dist: torch>=2.2; extra == 'torch'
